{
    "post1": ["가족여행", "비행기", "공항", "해외여행"],
    "post2": ["산책", "한라산", "풍경"],
    "post3": ["바다", "휴양"],
    "post4": ["도시관광", "맛집", "쇼핑"],
    "post5": ["문화재", "역사", "전통"],
    "post6": ["축제", "문화", "예술"],
    "post7": ["레저", "스포츠"],
    "post8": ["미식", "맛집", "휴양"],
    "post9": ["힐링", "공원", "산책"],
    "post10": ["등산", "한라산", "풍경"],
    "post11": ["해외여행", "비행기", "가족여행"],
    "post12": ["바다", "휴양", "캠핑"],
    "post13": ["축제", "전통", "역사"],
    "post14": ["도시관광", "쇼핑", "맛집"],
    "post15": ["레저", "스포츠", "재미"],
    "post16": ["문화", "예술", "전통"],
    "post17": ["공원", "산책", "풍경"],
    "post18": ["등산", "캠핑", "자연"],
    "post19": ["휴양", "가족여행", "바다", "힐링"],
    "post20": ["비행기", "해외여행", "사진"],
    "post21": ["쇼핑", "맛집", "미식"],
    "post22": ["문화재", "역사", "전통"],
    "post23": ["축제", "예술", "문화"],
    "post24": ["스포츠", "축구", "월드컵", "결승"],
    "post25": ["힐링", "휴양", "캠핑"],
    "post26": ["산책", "등산"],
    "post27": ["도시관광", "사진", "가족여행"],
    "post28": ["바다", "자연", "풍경"],
    "post29": ["문화", "축제", "전통"],
    "post30": ["레저", "스포츠", "힐링"]
}